demo/__init__.py
topix/__init__.py
topix/__main__.py
topix/emitter.py
topix/stream.py
topix/utils/__init__.py
topix-0.2.1.dist-info/LICENSE
topix-0.2.1.dist-info/METADATA
topix-0.2.1.dist-info/WHEEL
topix-0.2.1.dist-info/top_level.txt
topix-0.2.1.dist-info/RECORD
