Metadata-Version: 2.1
Name: topix
Version: 0.2.1
Summary: Topix is a functional microframework for working with Redis streams.
Home-page: https://github.com/madelyneriksen/topix
Author: Madelyn Eriksen
Author-email: opensource@madelyneriksen.com
License: UNKNOWN
Platform: UNKNOWN
Classifier: Programming Language :: Python :: 3
Classifier: License :: OSI Approved :: MIT License
Classifier: Operating System :: OS Independent
Requires-Dist: redis (>=3.0.0)
